pyamplitude/__init__.py
pyamplitude/amplituderedshift.py
pyamplitude/amplituderestapi.py
pyamplitude/apiresources.py
pyamplitude/behavioralcohortsapi.py
pyamplitude/exportapi.py
pyamplitude-1.2.0.dev1.dist-info/DESCRIPTION.rst
pyamplitude-1.2.0.dev1.dist-info/METADATA
pyamplitude-1.2.0.dev1.dist-info/RECORD
pyamplitude-1.2.0.dev1.dist-info/WHEEL
pyamplitude-1.2.0.dev1.dist-info/metadata.json
pyamplitude-1.2.0.dev1.dist-info/top_level.txt
