Metadata-Version: 2.0
Name: pyamplitude
Version: 1.2.0.dev1
Summary: A Python connector for Amplitude Analytics
Home-page: UNKNOWN
Author: Marcos Manuel Muraro
Author-email: mmmuraro@gmail.com
License: UNKNOWN
Platform: UNKNOWN
